aisentinel/__init__.py
aisentinel/config.py
aisentinel/embedded_db.py
aisentinel/governor.py
aisentinel/offline_mode.py
aisentinel/py.typed
aisentinel_sdk-0.1.3.dist-info/licenses/LICENSE
aisentinel_sdk-0.1.3.dist-info/METADATA
aisentinel_sdk-0.1.3.dist-info/WHEEL
aisentinel_sdk-0.1.3.dist-info/top_level.txt
aisentinel_sdk-0.1.3.dist-info/RECORD
