Metadata-Version: 2.4
Name: aisentinel-sdk
Version: 0.1.3
Summary: AISentinel Python SDK for AI governance and security
Author-email: AISentinel Team <team@aisentinel.info>
Maintainer-email: AISentinel Team <team@aisentinel.info>
License: MIT
Project-URL: Homepage, https://aisentinel.ai
Project-URL: Documentation, https://docs.aisentinel.ai/python
Project-URL: Repository, https://github.com/aisentinel/aisentinel-python-sdk
Project-URL: Issues, https://github.com/aisentinel/aisentinel-python-sdk/issues
Project-URL: Changelog, https://github.com/aisentinel/aisentinel-python-sdk/blob/main/CHANGELOG.md
Keywords: ai,governance,security,sdk,agent,audit
Classifier: Development Status :: 4 - Beta
Classifier: Intended Audience :: Developers
Classifier: License :: OSI Approved :: MIT License
Classifier: Operating System :: OS Independent
Classifier: Programming Language :: Python :: 3
Classifier: Programming Language :: Python :: 3.8
Classifier: Programming Language :: Python :: 3.9
Classifier: Programming Language :: Python :: 3.10
Classifier: Programming Language :: Python :: 3.11
Classifier: Programming Language :: Python :: 3.12
Classifier: Topic :: Security
Classifier: Topic :: Software Development :: Libraries :: Python Modules
Requires-Python: >=3.8
License-File: LICENSE
Requires-Dist: requests>=2.31.0
Provides-Extra: dev
Requires-Dist: pytest>=7.0.0; extra == "dev"
Requires-Dist: pytest-cov>=4.0.0; extra == "dev"
Requires-Dist: black>=23.0.0; extra == "dev"
Requires-Dist: isort>=5.12.0; extra == "dev"
Requires-Dist: mypy>=1.0.0; extra == "dev"
Requires-Dist: types-requests>=2.31.0; extra == "dev"
Requires-Dist: ruff>=0.1.0; extra == "dev"
Dynamic: license-file
